i2cpy/__init__.py
i2cpy/_version.py
i2cpy/errors.py
i2cpy/driver/abc.py
i2cpy/driver/ch341/__init__.py
i2cpy/driver/ch341/constants.py
i2cpy/driver/ch341/dll.py
i2cpy/driver/ch347/__init__.py
i2cpy/driver/ch347/dll.py
i2cpy-0.2.0.dist-info/licenses/LICENSE
i2cpy-0.2.0.dist-info/METADATA
i2cpy-0.2.0.dist-info/WHEEL
i2cpy-0.2.0.dist-info/top_level.txt
i2cpy-0.2.0.dist-info/RECORD
