Metadata-Version: 2.4
Name: i2cpy
Version: 0.2.0
Summary: Python I2C library supporting multiple driver implementations
Author-email: Zhenyi Zhou <iynehz@163.com>
License-Expression: MIT
Project-URL: Homepage, https://github.com/iynehz/i2cpy
Project-URL: Documentation, https://i2cpy.readthedocs.io/en/latest/
Project-URL: Repository, https://github.com/iynehz/i2cpy
Keywords: i2c,ch341,ch341a,ch347
Classifier: Development Status :: 5 - Production/Stable
Classifier: Programming Language :: Python
Classifier: Programming Language :: Python :: 3
Classifier: Programming Language :: Python :: 3 :: Only
Classifier: Topic :: Software Development
Classifier: Topic :: Scientific/Engineering
Classifier: Typing :: Typed
Requires-Python: >=3.9
License-File: LICENSE
Requires-Dist: typing_extensions>=4.6.0; python_version < "3.12"
Dynamic: license-file
